strawberry_utils/__init__.py
strawberry_utils/extensions/__init__.py
strawberry_utils/extensions/only_once_execution.py
strawberry_utils-0.0.1.dist-info/LICENSE
strawberry_utils-0.0.1.dist-info/METADATA
strawberry_utils-0.0.1.dist-info/WHEEL
strawberry_utils-0.0.1.dist-info/RECORD
