Metadata-Version: 2.3
Name: strawberry-utils
Version: 0.0.1
Summary: A module providing helpers for Strawberry
License: MIT
Keywords: strawberry,graphql,utils
Requires-Python: >=3.12
Classifier: Development Status :: 5 - Production/Stable
Classifier: Intended Audience :: Developers
Classifier: License :: OSI Approved :: MIT License
Classifier: Operating System :: OS Independent
Classifier: Programming Language :: Python :: 3
Classifier: Programming Language :: Python :: 3.12
Classifier: Programming Language :: Python :: 3.13
Classifier: Programming Language :: Python :: 3.14
Classifier: Programming Language :: Python :: 3.15
Classifier: Topic :: Internet
Classifier: Topic :: Software Development :: Libraries
Classifier: Topic :: Utilities
Classifier: Typing :: Typed
Requires-Dist: strawberry-graphql
Project-URL: Documentation, https://github.com/Arfey/strawberry-utils/blob/main/README.md
Project-URL: Homepage, https://github.com/Arfey/strawberry-utils
Project-URL: Repository, https://github.com/Arfey/strawberry-utils
